{
  "lambda": 1.0,
  "structure": [
    30,
    4,
    2,
    1
  ],
  "training": {
    "alpha": 1.0,
    "beta": 0.8,
    "mindelta": 1e-07
  },
  "folds": [
    {
      "j_t": 0.6599222369799304,
      "j_cv": 0.6638012882980675,
      "f1_score": 0.0
    },
    {
      "j_t": 0.6599310692278709,
      "j_cv": 0.663777905554584,
      "f1_score": 0.0
    },
    {
      "j_t": 0.6605587188742337,
      "j_cv": 0.6581727826338054,
      "f1_score": 0.0
    },
    {
      "j_t": 0.6605668523921288,
      "j_cv": 0.6581238536255917,
      "f1_score": 0.0
    },
    {
      "j_t": 0.6605838138968366,
      "j_cv": 0.6581130073176855,
      "f1_score": 0.0
    },
    {
      "j_t": 0.6605646190061906,
      "j_cv": 0.6581994920262683,
      "f1_score": 0.0
    },
    {
      "j_t": 0.6605587142145408,
      "j_cv": 0.658172748945076,
      "f1_score": 0.0
    },
    {
      "j_t": 0.6602490434377235,
      "j_cv": 0.6617157128244204,
      "f1_score": 0.0
    },
    {
      "j_t": 0.6602490444033774,
      "j_cv": 0.6617157184126038,
      "f1_score": 0.0
    },
    {
      "j_t": 0.6602099129269406,
      "j_cv": 0.6616541318203314,
      "f1_score": 0.0
    }
  ]
}